redisworker
