Metadata-Version: 1.1
Name: redisworker
Version: 0.2
Summary: Communicate jobs through redis
Home-page: https://github.com/metricstory/pyredisworker
Author: Will Schumacher
Author-email: will@metricstory.com
License: MIT
Download-URL: https://github.com/metricstory/redisworker/archive/0.2.tar.gz
Keywords: redis
Platform: UNKNOWN
